learnfetch/__init__.py
learnfetch/pesquisador.py
LearnFetch-1.0.1.dist-info/METADATA
LearnFetch-1.0.1.dist-info/WHEEL
LearnFetch-1.0.1.dist-info/top_level.txt
LearnFetch-1.0.1.dist-info/RECORD
