Metadata-Version: 2.1
Name: LearnFetch
Version: 1.0.1
Summary: Uma biblioteca para buscar e extrair dados do site 'Toda Matéria'.
Home-page: https://github.com/SaideOmaer1240/LearnFetch.git
Author: Saíde Omar Saíde
Author-email: saideomarsaideleon@gmail.com
Classifier: Programming Language :: Python :: 3
Classifier: Programming Language :: Python :: 3.12
Classifier: License :: OSI Approved :: MIT License
Classifier: Operating System :: OS Independent
Requires-Python: >=3.12.3
Requires-Dist: requests
Requires-Dist: beautifulsoup4
